vineseg/__init__.py
vineseg/__main__.py
vineseg/app.py
vineseg/label_file.py
vineseg/logger.py
vineseg/setup.py
vineseg/shape.py
vineseg/testing.py
ViNeSeg-0.0.6.dist-info/METADATA
ViNeSeg-0.0.6.dist-info/WHEEL
ViNeSeg-0.0.6.dist-info/top_level.txt
ViNeSeg-0.0.6.dist-info/RECORD
