Metadata-Version: 2.1
Name: ViNeSeg
Version: 0.0.6
Summary: Image Polygonal Annotation with Python combined with Auto-Segmentation
Home-page: https://github.com/NiRuff/IntelliPy
Author: Nicolas Ruffini, Nico Weber, Saleh Altahini, Anna Wierczeiko, Hendrik Backhaus
Author-email: nicolas.ruffini@lir-mainz.de
License: UNKNOWN
Platform: UNKNOWN
Classifier: Programming Language :: Python :: 3
Classifier: License :: OSI Approved :: MIT License
Classifier: Operating System :: OS Independent
Requires-Python: >=3.6
Requires-Dist: imgviz (>=0.11)
Requires-Dist: matplotlib (<3.3)
Requires-Dist: numpy
Requires-Dist: Pillow (>=2.8)
Requires-Dist: PyYAML
Requires-Dist: qtpy (!=1.11.2)
Requires-Dist: termcolor
Requires-Dist: monai
Requires-Dist: pandas
Requires-Dist: scikit-image (==0.18.1)
Requires-Dist: torchcontrib (==0.0.2)
Requires-Dist: shapely
